{
  "generated_at": "2026-04-28T12:01:18.681891+00:00",
  "workspace_root": "/mnt/c/projects/ai-frendly-datahub",
  "inputs": {
    "projects_json": "radar-dashboard/data/projects.json",
    "summary_json": "radar-dashboard/data/summary.json",
    "classification_json": "radar-dashboard/data/classification.json"
  },
  "summary": {
    "project_count": 37,
    "taxonomy_repo_count": 40,
    "shared_taxonomy_repo_count": 3,
    "unmatched_project_count": 0,
    "unmatched_projects": [],
    "article_total": 5351,
    "matched_total": 5188,
    "overall_match_rate": 97.0,
    "dashboard_generated_at": "2026-04-28T11:59:58.828065+00:00",
    "project_data_generated_at": "2026-04-28T11:59:58.827887+00:00",
    "classification_generated_at": "2026-04-28T11:59:40.840790+00:00",
    "collection_error_total": 0,
    "freshness_gap_total": 86,
    "disabled_source_total": 196,
    "disabled_source_classification_summary": {
      "total_disabled_count": 197,
      "bucket_totals": {
        "awaiting_url_replacement": 57,
        "awaiting_secret": 17,
        "awaiting_smoke_test": 4,
        "upstream_section_missing": 1,
        "awaiting_partnership_review": 0,
        "accepted_backlog": 118
      },
      "repo_count_with_disabled_sources": 32
    },
    "repos_with_errors": 0,
    "repos_with_freshness_gap": 17,
    "repos_with_disabled_sources": 31,
    "average_risk_score": 24.3,
    "operational_priority_counts": {
      "P1": 13,
      "P0": 4,
      "P2": 16,
      "P3": 4
    },
    "taxonomy_priority_counts": {
      "T1": 26,
      "T3": 11
    },
    "focus_area_counts": {
      "freshness_coverage": 9,
      "collector_repair": 4,
      "disabled_source_governance": 6,
      "taxonomy_enrichment": 13,
      "tracked_source_coverage": 3,
      "stable": 2
    },
    "primary_motion_counts": {
      "conversion": 9,
      "compliance-risk": 17,
      "intelligence": 10,
      "attention": 1
    },
    "governance_counts": {
      "medium": 21,
      "high": 9,
      "low": 7
    },
    "readiness_counts": {
      "watch": 25,
      "ready": 11,
      "upgrade": 1
    },
    "source_status_counts": {
      "л¶Ҳк· нҳ•": 24,
      "к°•н•Ё": 12,
      "ліҙк°•мҡ°м„ ": 1
    },
    "evidence_strategy_counts": {
      "official-operational": 23,
      "balanced-mixed": 12,
      "market-led": 1,
      "attention-led": 1
    },
    "layer_gap_counts": {
      "community": 2,
      "market": 12
    },
    "top_risk_repos": [
      "QueueRadar",
      "PropertyRadar",
      "RefundRadar",
      "ArtRadar",
      "BookRadar",
      "PaperworkRadar",
      "WineRadar",
      "PolicyRadar",
      "TrustRadar",
      "CollaborationMCPRadar"
    ],
    "top_taxonomy_repos": [
      "MiscMCPRadar",
      "PropertyRadar",
      "GovRadar",
      "JobRadar",
      "PaperworkRadar",
      "PolicyRadar",
      "RefundRadar",
      "CollaborationMCPRadar",
      "CommerceMCPRadar",
      "FinanceTaxMCPRadar",
      "KoreanNLPMCPRadar",
      "LegalGovMCPRadar"
    ]
  },
  "groups": {
    "repo_class": [
      {
        "key": "standard-radar",
        "project_count": 32,
        "article_count": 4889,
        "matched_count": 4749,
        "match_rate": 97.1,
        "collection_errors": 0,
        "freshness_gap": 82,
        "disabled_sources": 154,
        "average_risk_score": 25.8,
        "watch_count": 24,
        "p0_count": 3,
        "t1_count": 25,
        "missing_layer_counts": {
          "community": 2,
          "market": 12
        }
      },
      {
        "key": "advanced-radar",
        "project_count": 5,
        "article_count": 462,
        "matched_count": 439,
        "match_rate": 95.0,
        "collection_errors": 0,
        "freshness_gap": 4,
        "disabled_sources": 42,
        "average_risk_score": 14.6,
        "watch_count": 1,
        "p0_count": 1,
        "t1_count": 1,
        "missing_layer_counts": {}
      }
    ],
    "primary_motion": [
      {
        "key": "compliance-risk",
        "project_count": 17,
        "article_count": 951,
        "matched_count": 864,
        "match_rate": 90.9,
        "collection_errors": 0,
        "freshness_gap": 33,
        "disabled_sources": 57,
        "average_risk_score": 27.5,
        "watch_count": 14,
        "p0_count": 2,
        "t1_count": 15,
        "missing_layer_counts": {
          "market": 12,
          "community": 1
        }
      },
      {
        "key": "conversion",
        "project_count": 9,
        "article_count": 1173,
        "matched_count": 1124,
        "match_rate": 95.8,
        "collection_errors": 0,
        "freshness_gap": 25,
        "disabled_sources": 68,
        "average_risk_score": 24.8,
        "watch_count": 7,
        "p0_count": 2,
        "t1_count": 7,
        "missing_layer_counts": {
          "community": 1
        }
      },
      {
        "key": "intelligence",
        "project_count": 10,
        "article_count": 3027,
        "matched_count": 3000,
        "match_rate": 99.1,
        "collection_errors": 0,
        "freshness_gap": 28,
        "disabled_sources": 71,
        "average_risk_score": 20.9,
        "watch_count": 4,
        "p0_count": 0,
        "t1_count": 4,
        "missing_layer_counts": {}
      },
      {
        "key": "attention",
        "project_count": 1,
        "article_count": 200,
        "matched_count": 200,
        "match_rate": 100.0,
        "collection_errors": 0,
        "freshness_gap": 0,
        "disabled_sources": 0,
        "average_risk_score": 0.0,
        "watch_count": 0,
        "p0_count": 0,
        "t1_count": 0,
        "missing_layer_counts": {}
      }
    ],
    "governance_profile": [
      {
        "key": "high",
        "project_count": 9,
        "article_count": 1420,
        "matched_count": 1284,
        "match_rate": 90.4,
        "collection_errors": 0,
        "freshness_gap": 40,
        "disabled_sources": 66,
        "average_risk_score": 28.6,
        "watch_count": 6,
        "p0_count": 4,
        "t1_count": 6,
        "missing_layer_counts": {
          "community": 1
        }
      },
      {
        "key": "medium",
        "project_count": 21,
        "article_count": 1461,
        "matched_count": 1455,
        "match_rate": 99.6,
        "collection_errors": 0,
        "freshness_gap": 29,
        "disabled_sources": 99,
        "average_risk_score": 24.6,
        "watch_count": 16,
        "p0_count": 0,
        "t1_count": 17,
        "missing_layer_counts": {
          "market": 12,
          "community": 1
        }
      },
      {
        "key": "low",
        "project_count": 7,
        "article_count": 2470,
        "matched_count": 2449,
        "match_rate": 99.1,
        "collection_errors": 0,
        "freshness_gap": 17,
        "disabled_sources": 31,
        "average_risk_score": 18.1,
        "watch_count": 3,
        "p0_count": 0,
        "t1_count": 3,
        "missing_layer_counts": {}
      }
    ],
    "evidence_strategy": [
      {
        "key": "balanced-mixed",
        "project_count": 12,
        "article_count": 44,
        "matched_count": 44,
        "match_rate": 100.0,
        "collection_errors": 0,
        "freshness_gap": 0,
        "disabled_sources": 21,
        "average_risk_score": 26.8,
        "watch_count": 11,
        "p0_count": 0,
        "t1_count": 12,
        "missing_layer_counts": {
          "market": 12,
          "community": 1
        }
      },
      {
        "key": "official-operational",
        "project_count": 23,
        "article_count": 5007,
        "matched_count": 4844,
        "match_rate": 96.7,
        "collection_errors": 0,
        "freshness_gap": 86,
        "disabled_sources": 175,
        "average_risk_score": 25.1,
        "watch_count": 14,
        "p0_count": 4,
        "t1_count": 14,
        "missing_layer_counts": {
          "community": 1
        }
      },
      {
        "key": "attention-led",
        "project_count": 1,
        "article_count": 200,
        "matched_count": 200,
        "match_rate": 100.0,
        "collection_errors": 0,
        "freshness_gap": 0,
        "disabled_sources": 0,
        "average_risk_score": 0.0,
        "watch_count": 0,
        "p0_count": 0,
        "t1_count": 0,
        "missing_layer_counts": {}
      },
      {
        "key": "market-led",
        "project_count": 1,
        "article_count": 100,
        "matched_count": 100,
        "match_rate": 100.0,
        "collection_errors": 0,
        "freshness_gap": 0,
        "disabled_sources": 0,
        "average_risk_score": 0.0,
        "watch_count": 0,
        "p0_count": 0,
        "t1_count": 0,
        "missing_layer_counts": {}
      }
    ],
    "readiness_status": [
      {
        "key": "watch",
        "project_count": 25,
        "article_count": 2899,
        "matched_count": 2842,
        "match_rate": 98.0,
        "collection_errors": 0,
        "freshness_gap": 56,
        "disabled_sources": 141,
        "average_risk_score": 28.4,
        "watch_count": 25,
        "p0_count": 1,
        "t1_count": 25,
        "missing_layer_counts": {
          "community": 1,
          "market": 11
        }
      },
      {
        "key": "upgrade",
        "project_count": 1,
        "article_count": 0,
        "matched_count": 0,
        "match_rate": null,
        "collection_errors": 0,
        "freshness_gap": 0,
        "disabled_sources": 1,
        "average_risk_score": 27.0,
        "watch_count": 0,
        "p0_count": 0,
        "t1_count": 1,
        "missing_layer_counts": {
          "community": 1,
          "market": 1
        }
      },
      {
        "key": "ready",
        "project_count": 11,
        "article_count": 2452,
        "matched_count": 2346,
        "match_rate": 95.7,
        "collection_errors": 0,
        "freshness_gap": 30,
        "disabled_sources": 54,
        "average_risk_score": 14.9,
        "watch_count": 0,
        "p0_count": 3,
        "t1_count": 0,
        "missing_layer_counts": {}
      }
    ],
    "source_status": [
      {
        "key": "л¶Ҳк· нҳ•",
        "project_count": 24,
        "article_count": 2899,
        "matched_count": 2842,
        "match_rate": 98.0,
        "collection_errors": 0,
        "freshness_gap": 56,
        "disabled_sources": 141,
        "average_risk_score": 28.8,
        "watch_count": 24,
        "p0_count": 1,
        "t1_count": 24,
        "missing_layer_counts": {
          "community": 1,
          "market": 11
        }
      },
      {
        "key": "ліҙк°•мҡ°м„ ",
        "project_count": 1,
        "article_count": 0,
        "matched_count": 0,
        "match_rate": null,
        "collection_errors": 0,
        "freshness_gap": 0,
        "disabled_sources": 1,
        "average_risk_score": 27.0,
        "watch_count": 0,
        "p0_count": 0,
        "t1_count": 1,
        "missing_layer_counts": {
          "community": 1,
          "market": 1
        }
      },
      {
        "key": "к°•н•Ё",
        "project_count": 12,
        "article_count": 2452,
        "matched_count": 2346,
        "match_rate": 95.7,
        "collection_errors": 0,
        "freshness_gap": 30,
        "disabled_sources": 54,
        "average_risk_score": 15.2,
        "watch_count": 1,
        "p0_count": 3,
        "t1_count": 1,
        "missing_layer_counts": {}
      }
    ]
  },
  "repos": [
    {
      "repo": "QueueRadar",
      "display_name": "Queue",
      "category": "queue",
      "repo_class": "standard-radar",
      "domain_family": "operations-queues",
      "primary_motion": "conversion",
      "governance_profile": "medium",
      "evidence_strategy": "official-operational",
      "readiness_status": "watch",
      "source_status": "л¶Ҳк· нҳ•",
      "available_layers": [
        "community",
        "market",
        "official",
        "operational"
      ],
      "missing_layers": [],
      "layer_counts": {
        "community": 1,
        "market": 11,
        "official": 14,
        "operational": 12
      },
      "next_step": "нӢ°мј“ к°ҖкІ©, мҳҲм•Ҫ мҠ¬лЎҜ, лӮ м”ЁВ·мӢңмҰҲл„җлҰ¬нӢ°лҘј н•©міҗ мҳҲмёЎл Ҙмқ„ лҶ’мқёлӢӨ.",
      "quality_score": 85,
      "taxonomy_priority_score": 26,
      "article_count": 200,
      "matched_count": 200,
      "match_rate": 100.0,
      "source_count": 8,
      "dashboard_status": "active",
      "last_updated": "2026-04-25",
      "warnings": [
        "quality freshness gaps: stale=12, missing=0, unknown_event_date=0",
        "quality report has 16 disabled source(s)"
      ],
      "warning_count": 2,
      "quality_origin": "QueueRadar/reports/queue_20260428_quality.json",
      "data_origin": "QueueRadar/reports/queue_20260425_summary.json",
      "tracked_coverage_pct": 52.2,
      "freshness_coverage_pct": 0.0,
      "disabled_source_classification": {
        "awaiting_url_replacement": 2,
        "awaiting_secret": 0,
        "awaiting_smoke_test": 0,
        "upstream_section_missing": 0,
        "awaiting_partnership_review": 0,
        "accepted_backlog": 14
      },
      "disabled_source_classification_total": 16,
      "collection_errors": 0,
      "freshness_gap": 12,
      "stale_sources": 12,
      "missing_sources": 0,
      "unknown_event_date_sources": 0,
      "disabled_sources": 16,
      "total_sources": 39,
      "enabled_sources": 23,
      "tracked_sources": 12,
      "fresh_sources": 0,
      "not_tracked_sources": 11,
      "operational_priority": "P1",
      "taxonomy_priority": "T1",
      "risk_score": 44,
      "focus_area": "freshness_coverage"
    },
    {
      "repo": "PropertyRadar",
      "display_name": "Property",
      "category": "property",
      "repo_class": "standard-radar",
      "domain_family": "property",
      "primary_motion": "conversion",
      "governance_profile": "high",
      "evidence_strategy": "official-operational",
      "readiness_status": "watch",
      "source_status": "л¶Ҳк· нҳ•",
      "available_layers": [
        "market",
        "official",
        "operational"
      ],
      "missing_layers": [
        "community"
      ],
      "layer_counts": {
        "market": 9,
        "official": 2,
        "operational": 1
      },
      "next_step": "мӢӨкұ°лһҳ, л¶„м–‘ кІҪмҹҒлҘ , л§Өл¬ј inventory, мқён—Ҳк°ҖВ·мӨҖкіө лҚ°мқҙн„°лҘј лҚ”н•ңлӢӨ.",
      "quality_score": 85,
      "taxonomy_priority_score": 36,
      "article_count": 146,
      "matched_count": 120,
      "match_rate": 82.2,
      "source_count": 8,
      "dashboard_status": "active",
      "last_updated": "2026-04-25",
      "warnings": [
        "quality freshness gaps: stale=2, missing=0, unknown_event_date=0",
        "quality report has 8 disabled source(s)"
      ],
      "warning_count": 2,
      "quality_origin": "PropertyRadar/reports/property_20260428_quality.json",
      "data_origin": "PropertyRadar/reports/property_20260425_summary.json",
      "tracked_coverage_pct": 66.7,
      "freshness_coverage_pct": 16.7,
      "disabled_source_classification": {
        "awaiting_url_replacement": 0,
        "awaiting_secret": 0,
        "awaiting_smoke_test": 0,
        "upstream_section_missing": 0,
        "awaiting_partnership_review": 0,
        "accepted_backlog": 8
      },
      "disabled_source_classification_total": 8,
      "collection_errors": 0,
      "freshness_gap": 2,
      "stale_sources": 2,
      "missing_sources": 0,
      "unknown_event_date_sources": 0,
      "disabled_sources": 8,
      "total_sources": 17,
      "enabled_sources": 9,
      "tracked_sources": 6,
      "fresh_sources": 1,
      "not_tracked_sources": 5,
      "operational_priority": "P0",
      "taxonomy_priority": "T1",
      "risk_score": 43,
      "focus_area": "collector_repair"
    },
    {
      "repo": "RefundRadar",
      "display_name": "Refund",
      "category": "refund",
      "repo_class": "standard-radar",
      "domain_family": "consumer-rights",
      "primary_motion": "compliance-risk",
      "governance_profile": "high",
      "evidence_strategy": "official-operational",
      "readiness_status": "watch",
      "source_status": "л¶Ҳк· нҳ•",
      "available_layers": [
        "market",
        "official",
        "operational"
      ],
      "missing_layers": [],
      "layer_counts": {
        "market": 19,
        "official": 9,
        "operational": 8
      },
      "next_step": "refund_claim_window, recall_refund_notice, complaint_resolution event modelмқ„ кІҖмҰқ мӮ°м¶ңл¬јм—җ м—°кІ°н•ҳкі  seller/airline policy diff нӣ„ліҙлҠ” source_backlogм—җм„ң кІҖмҰқ нӣ„ нҷңм„ұнҷ”н•ңлӢӨ.",
      "quality_score": 85,
      "taxonomy_priority_score": 32,
      "article_count": 129,
      "matched_count": 129,
      "match_rate": 100.0,
      "source_count": 14,
      "dashboard_status": "active",
      "last_updated": "2026-04-25",
      "warnings": [
        "quality freshness gaps: stale=6, missing=0, unknown_event_date=0",
        "quality report has 20 disabled source(s)"
      ],
      "warning_count": 2,
      "quality_origin": "RefundRadar/reports/refund_20260428_quality.json",
      "data_origin": "RefundRadar/reports/refund_20260425_summary.json",
      "tracked_coverage_pct": 31.6,
      "freshness_coverage_pct": 0.0,
      "disabled_source_classification": {
        "awaiting_url_replacement": 3,
        "awaiting_secret": 0,
        "awaiting_smoke_test": 0,
        "upstream_section_missing": 0,
        "awaiting_partnership_review": 0,
        "accepted_backlog": 17
      },
      "disabled_source_classification_total": 20,
      "collection_errors": 0,
      "freshness_gap": 6,
      "stale_sources": 6,
      "missing_sources": 0,
      "unknown_event_date_sources": 0,
      "disabled_sources": 20,
      "total_sources": 39,
      "enabled_sources": 19,
      "tracked_sources": 6,
      "fresh_sources": 0,
      "not_tracked_sources": 13,
      "operational_priority": "P1",
      "taxonomy_priority": "T1",
      "risk_score": 40,
      "focus_area": "freshness_coverage"
    },
    {
      "repo": "ArtRadar",
      "display_name": "Art",
      "category": "art",
      "repo_class": "standard-radar",
      "domain_family": "culture",
      "primary_motion": "intelligence",
      "governance_profile": "low",
      "evidence_strategy": "official-operational",
      "readiness_status": "watch",
      "source_status": "л¶Ҳк· нҳ•",
      "available_layers": [
        "community",
        "market",
        "official",
        "operational"
      ],
      "missing_layers": [],
      "layer_counts": {
        "community": 6,
        "market": 35,
        "official": 9,
        "operational": 2
      },
      "next_step": "кІҪл§Ө лӮҷм°°к°Җ, нӢ°мј“ нҢҗл§Ө, м•„нҠёнҺҳм–ҙ м°ёк°ҖмӮ¬ к°ҷмқҖ кұ°лһҳнҳ• мҶҢмҠӨлҘј л„Јм–ҙ мӢңмһҘм„ұ нҢҗлӢЁмқ„ к°•нҷ”н•ңлӢӨ.",
      "quality_score": 85,
      "taxonomy_priority_score": 22,
      "article_count": 200,
      "matched_count": 186,
      "match_rate": 93.0,
      "source_count": 30,
      "dashboard_status": "active",
      "last_updated": "2026-04-24",
      "warnings": [
        "quality freshness gaps: stale=7, missing=0, unknown_event_date=0",
        "quality report has 4 disabled source(s)"
      ],
      "warning_count": 2,
      "quality_origin": "ArtRadar/reports/art_20260428_quality.json",
      "data_origin": "ArtRadar/reports/art_20260424_summary.json",
      "tracked_coverage_pct": 31.2,
      "freshness_coverage_pct": 30.0,
      "disabled_source_classification": {
        "awaiting_url_replacement": 3,
        "awaiting_secret": 0,
        "awaiting_smoke_test": 0,
        "upstream_section_missing": 0,
        "awaiting_partnership_review": 0,
        "accepted_backlog": 1
      },
      "disabled_source_classification_total": 4,
      "collection_errors": 0,
      "freshness_gap": 7,
      "stale_sources": 7,
      "missing_sources": 0,
      "unknown_event_date_sources": 0,
      "disabled_sources": 4,
      "total_sources": 36,
      "enabled_sources": 32,
      "tracked_sources": 10,
      "fresh_sources": 3,
      "not_tracked_sources": 22,
      "operational_priority": "P1",
      "taxonomy_priority": "T1",
      "risk_score": 31,
      "focus_area": "freshness_coverage"
    },
    {
      "repo": "BookRadar",
      "display_name": "Book",
      "category": "book",
      "repo_class": "standard-radar",
      "domain_family": "publishing",
      "primary_motion": "intelligence",
      "governance_profile": "low",
      "evidence_strategy": "official-operational",
      "readiness_status": "watch",
      "source_status": "л¶Ҳк· нҳ•",
      "available_layers": [
        "community",
        "market",
        "official",
        "operational"
      ],
      "missing_layers": [],
      "layer_counts": {
        "community": 10,
        "market": 12,
        "official": 2,
        "operational": 1
      },
      "next_step": "лҸ„м„ң нҢҗл§Ө лһӯнӮ№ м¶”мқҙ, лҸ„м„ңкҙҖ лҢҖм¶ң, мһ‘к°Җ н–үмӮ¬ мқјм •мқ„ лҚ”н•ҙ мҲҳмҡ” мҳҲмёЎл Ҙмқ„ мҳ¬лҰ°лӢӨ.",
      "quality_score": 85,
      "taxonomy_priority_score": 22,
      "article_count": 485,
      "matched_count": 485,
      "match_rate": 100.0,
      "source_count": 19,
      "dashboard_status": "active",
      "last_updated": "2026-04-25",
      "warnings": [
        "quality report has 12 disabled source(s)"
      ],
      "warning_count": 1,
      "quality_origin": "BookRadar/reports/book_20260428_quality.json",
      "data_origin": "BookRadar/reports/book_20260425_summary.json",
      "tracked_coverage_pct": 5.0,
      "freshness_coverage_pct": 0.0,
      "disabled_source_classification": {
        "awaiting_url_replacement": 7,
        "awaiting_secret": 0,
        "awaiting_smoke_test": 0,
        "upstream_section_missing": 0,
        "awaiting_partnership_review": 0,
        "accepted_backlog": 5
      },
      "disabled_source_classification_total": 12,
      "collection_errors": 0,
      "freshness_gap": 0,
      "stale_sources": 0,
      "missing_sources": 0,
      "unknown_event_date_sources": 0,
      "disabled_sources": 12,
      "total_sources": 32,
      "enabled_sources": 20,
      "tracked_sources": 1,
      "fresh_sources": 0,
      "not_tracked_sources": 20,
      "operational_priority": "P1",
      "taxonomy_priority": "T1",
      "risk_score": 31,
      "focus_area": "disabled_source_governance"
    },
    {
      "repo": "PaperworkRadar",
      "display_name": "Paperwork",
      "category": "paperwork",
      "repo_class": "standard-radar",
      "domain_family": "administrative-documents",
      "primary_motion": "compliance-risk",
      "governance_profile": "high",
      "evidence_strategy": "official-operational",
      "readiness_status": "watch",
      "source_status": "л¶Ҳк· нҳ•",
      "available_layers": [
        "community",
        "market",
        "official",
        "operational"
      ],
      "missing_layers": [],
      "layer_counts": {
        "community": 4,
        "market": 18,
        "official": 15,
        "operational": 15
      },
      "next_step": "form_revision, filing_deadline, portal_service_change event modelмқ„ кІҖмҰқ мӮ°м¶ңл¬јкіј document hash diff м ҖмһҘ кІҪлЎңм—җ м—°кІ°н•ңлӢӨ.",
      "quality_score": 85,
      "taxonomy_priority_score": 32,
      "article_count": 200,
      "matched_count": 197,
      "match_rate": 98.5,
      "source_count": 17,
      "dashboard_status": "active",
      "last_updated": "2026-04-25",
      "warnings": [
        "quality freshness gaps: stale=8, missing=0, unknown_event_date=0",
        "quality report has 8 disabled source(s)"
      ],
      "warning_count": 2,
      "quality_origin": "PaperworkRadar/reports/paperwork_20260428_quality.json",
      "data_origin": "PaperworkRadar/reports/paperwork_20260425_summary.json",
      "tracked_coverage_pct": 63.6,
      "freshness_coverage_pct": 42.9,
      "disabled_source_classification": {
        "awaiting_url_replacement": 8,
        "awaiting_secret": 0,
        "awaiting_smoke_test": 0,
        "upstream_section_missing": 0,
        "awaiting_partnership_review": 0,
        "accepted_backlog": 0
      },
      "disabled_source_classification_total": 8,
      "collection_errors": 0,
      "freshness_gap": 8,
      "stale_sources": 8,
      "missing_sources": 0,
      "unknown_event_date_sources": 0,
      "disabled_sources": 8,
      "total_sources": 30,
      "enabled_sources": 22,
      "tracked_sources": 14,
      "fresh_sources": 6,
      "not_tracked_sources": 8,
      "operational_priority": "P1",
      "taxonomy_priority": "T1",
      "risk_score": 31,
      "focus_area": "freshness_coverage"
    },
    {
      "repo": "WineRadar",
      "display_name": "Wine",
      "category": "wine",
      "repo_class": "advanced-radar",
      "domain_family": "wine-trade",
      "primary_motion": "intelligence",
      "governance_profile": "medium",
      "evidence_strategy": "official-operational",
      "readiness_status": "ready",
      "source_status": "к°•н•Ё",
      "available_layers": [
        "community",
        "market",
        "official",
        "operational"
      ],
      "missing_layers": [],
      "layer_counts": {
        "community": 5,
        "market": 49,
        "official": 15,
        "operational": 2
      },
      "next_step": "auction price, л ҲмҠӨнҶ лһ‘ мҷҖмқёлҰ¬мҠӨнҠё ліҖлҸҷ, importer portfolio sales к°ҷмқҖ кұ°лһҳ мӢ нҳёлҘј лҚ”н•ңлӢӨ.",
      "quality_score": 95,
      "taxonomy_priority_score": 8,
      "article_count": 62,
      "matched_count": 62,
      "match_rate": 100.0,
      "source_count": 17,
      "dashboard_status": "active",
      "last_updated": "2026-04-25",
      "warnings": [
        "quality freshness gaps: stale=4, missing=0, unknown_event_date=0",
        "quality report has 27 disabled source(s)"
      ],
      "warning_count": 2,
      "quality_origin": "WineRadar/reports/wine_quality.json",
      "data_origin": "WineRadar/reports/wine_20260425_summary.json",
      "tracked_coverage_pct": 81.8,
      "freshness_coverage_pct": 88.9,
      "disabled_source_classification": {
        "awaiting_url_replacement": 8,
        "awaiting_secret": 0,
        "awaiting_smoke_test": 0,
        "upstream_section_missing": 0,
        "awaiting_partnership_review": 0,
        "accepted_backlog": 19
      },
      "disabled_source_classification_total": 27,
      "collection_errors": 0,
      "freshness_gap": 4,
      "stale_sources": 4,
      "missing_sources": 0,
      "unknown_event_date_sources": 0,
      "disabled_sources": 27,
      "total_sources": 71,
      "enabled_sources": 44,
      "tracked_sources": 36,
      "fresh_sources": 32,
      "not_tracked_sources": 8,
      "operational_priority": "P1",
      "taxonomy_priority": "T3",
      "risk_score": 31,
      "focus_area": "disabled_source_governance"
    },
    {
      "repo": "PolicyRadar",
      "display_name": "Policy",
      "category": "policy",
      "repo_class": "standard-radar",
      "domain_family": "policy-regulation",
      "primary_motion": "compliance-risk",
      "governance_profile": "high",
      "evidence_strategy": "official-operational",
      "readiness_status": "watch",
      "source_status": "л¶Ҳк· нҳ•",
      "available_layers": [
        "community",
        "market",
        "official",
        "operational"
      ],
      "missing_layers": [],
      "layer_counts": {
        "community": 3,
        "market": 29,
        "official": 19,
        "operational": 18
      },
      "next_step": "public_consultation, enforcement_action, policy_effective_date, platform_policy_change event modelмқ„ кІҖмҰқ мӮ°м¶ңл¬јм—җ м—°кІ°н•ҳкі  Regulations.gov/мһ…лІ•мҳҲкі /FTC/PIPC нӣ„ліҙлҠ” source_backlogм—җм„ң кІҖмҰқ нӣ„ нҷңм„ұнҷ”н•ңлӢӨ.",
      "quality_score": 85,
      "taxonomy_priority_score": 32,
      "article_count": 185,
      "matched_count": 171,
      "match_rate": 92.4,
      "source_count": 17,
      "dashboard_status": "active",
      "last_updated": "2026-04-25",
      "warnings": [
        "quality freshness gaps: stale=5, missing=0, unknown_event_date=0",
        "quality report has 5 disabled source(s)"
      ],
      "warning_count": 2,
      "quality_origin": "PolicyRadar/reports/policy_20260428_quality.json",
      "data_origin": "PolicyRadar/reports/policy_20260425_summary.json",
      "tracked_coverage_pct": 27.6,
      "freshness_coverage_pct": 37.5,
      "disabled_source_classification": {
        "awaiting_url_replacement": 2,
        "awaiting_secret": 0,
        "awaiting_smoke_test": 1,
        "upstream_section_missing": 0,
        "awaiting_partnership_review": 0,
        "accepted_backlog": 2
      },
      "disabled_source_classification_total": 5,
      "collection_errors": 0,
      "freshness_gap": 5,
      "stale_sources": 5,
      "missing_sources": 0,
      "unknown_event_date_sources": 0,
      "disabled_sources": 5,
      "total_sources": 34,
      "enabled_sources": 29,
      "tracked_sources": 8,
      "fresh_sources": 3,
      "not_tracked_sources": 21,
      "operational_priority": "P1",
      "taxonomy_priority": "T1",
      "risk_score": 30,
      "focus_area": "freshness_coverage"
    },
    {
      "repo": "TrustRadar",
      "display_name": "Trust",
      "category": "trust",
      "repo_class": "standard-radar",
      "domain_family": "security-privacy",
      "primary_motion": "compliance-risk",
      "governance_profile": "high",
      "evidence_strategy": "official-operational",
      "readiness_status": "ready",
      "source_status": "к°•н•Ё",
      "available_layers": [
        "community",
        "market",
        "official",
        "operational"
      ],
      "missing_layers": [],
      "layer_counts": {
        "community": 3,
        "market": 25,
        "official": 7,
        "operational": 13
      },
      "next_step": "incident_disclosure, status_page_incident, enforcement_action, consumer_complaint, ai_asset_risk event modelмқ„ кІҖмҰқ мӮ°м¶ңл¬јм—җ м—°кІ°н•ҳкі  м»Өл®ӨлӢҲнӢ° мӢ нҳёлҠ” official_confirmation_required мғҒнғңлЎңл§Ң лі‘н•©н•ңлӢӨ.",
      "quality_score": 95,
      "taxonomy_priority_score": 10,
      "article_count": 193,
      "matched_count": 160,
      "match_rate": 82.9,
      "source_count": 19,
      "dashboard_status": "active",
      "last_updated": "2026-04-25",
      "warnings": [
        "quality freshness gaps: stale=12, missing=0, unknown_event_date=0",
        "quality report has 2 disabled source(s)"
      ],
      "warning_count": 2,
      "quality_origin": "TrustRadar/reports/trust_20260428_quality.json",
      "data_origin": "TrustRadar/reports/trust_20260425_summary.json",
      "tracked_coverage_pct": 48.0,
      "freshness_coverage_pct": 0.0,
      "disabled_source_classification": {
        "awaiting_url_replacement": 2,
        "awaiting_secret": 0,
        "awaiting_smoke_test": 0,
        "upstream_section_missing": 0,
        "awaiting_partnership_review": 0,
        "accepted_backlog": 0
      },
      "disabled_source_classification_total": 2,
      "collection_errors": 0,
      "freshness_gap": 12,
      "stale_sources": 12,
      "missing_sources": 0,
      "unknown_event_date_sources": 0,
      "disabled_sources": 2,
      "total_sources": 27,
      "enabled_sources": 25,
      "tracked_sources": 12,
      "fresh_sources": 0,
      "not_tracked_sources": 13,
      "operational_priority": "P0",
      "taxonomy_priority": "T3",
      "risk_score": 29,
      "focus_area": "collector_repair"
    },
    {
      "repo": "CollaborationMCPRadar",
      "display_name": "CollaborationMCP",
      "category": "collaboration_mcp",
      "repo_class": "standard-radar",
      "domain_family": "mcp-collaboration",
      "primary_motion": "compliance-risk",
      "governance_profile": "medium",
      "evidence_strategy": "balanced-mixed",
      "readiness_status": "watch",
      "source_status": "л¶Ҳк· нҳ•",
      "available_layers": [
        "community"
      ],
      "missing_layers": [
        "market"
      ],
      "layer_counts": {
        "community": 1
      },
      "next_step": "awesome-mcp-korea community seedлҘј GitHub repository metadataмҷҖ security/risk cross-checkлЎң ліҙк°•н•ңлӢӨ.",
      "quality_score": 80,
      "taxonomy_priority_score": 30,
      "article_count": 4,
      "matched_count": 4,
      "match_rate": 100.0,
      "source_count": 1,
      "dashboard_status": "active",
      "last_updated": "2026-04-24",
      "warnings": [
        "quality report has 2 disabled source(s)"
      ],
      "warning_count": 1,
      "quality_origin": "CollaborationMCPRadar/reports/collaboration_mcp_20260428_quality.json",
      "data_origin": "CollaborationMCPRadar/reports/collaboration_mcp_20260424_summary.json",
      "tracked_coverage_pct": 100.0,
      "freshness_coverage_pct": 33.3,
      "disabled_source_classification": {
        "awaiting_url_replacement": 0,
        "awaiting_secret": 1,
        "awaiting_smoke_test": 1,
        "upstream_section_missing": 0,
        "awaiting_partnership_review": 0,
        "accepted_backlog": 0
      },
      "disabled_source_classification_total": 2,
      "collection_errors": 0,
      "freshness_gap": 0,
      "stale_sources": 0,
      "missing_sources": 0,
      "unknown_event_date_sources": 0,
      "disabled_sources": 2,
      "total_sources": 3,
      "enabled_sources": 3,
      "tracked_sources": 3,
      "fresh_sources": 1,
      "not_tracked_sources": 0,
      "operational_priority": "P2",
      "taxonomy_priority": "T1",
      "risk_score": 27,
      "focus_area": "taxonomy_enrichment"
    },
    {
      "repo": "CommerceMCPRadar",
      "display_name": "CommerceMCP",
      "category": "commerce_mcp",
      "repo_class": "standard-radar",
      "domain_family": "mcp-commerce",
      "primary_motion": "compliance-risk",
      "governance_profile": "medium",
      "evidence_strategy": "balanced-mixed",
      "readiness_status": "watch",
      "source_status": "л¶Ҳк· нҳ•",
      "available_layers": [
        "community"
      ],
      "missing_layers": [
        "market"
      ],
      "layer_counts": {
        "community": 1
      },
      "next_step": "awesome-mcp-korea community seedлҘј GitHub repository metadataмҷҖ security/risk cross-checkлЎң ліҙк°•н•ңлӢӨ.",
      "quality_score": 80,
      "taxonomy_priority_score": 30,
      "article_count": 2,
      "matched_count": 2,
      "match_rate": 100.0,
      "source_count": 1,
      "dashboard_status": "active",
      "last_updated": "2026-04-24",
      "warnings": [
        "quality report has 2 disabled source(s)"
      ],
      "warning_count": 1,
      "quality_origin": "CommerceMCPRadar/reports/commerce_mcp_20260428_quality.json",
      "data_origin": "CommerceMCPRadar/reports/commerce_mcp_20260424_summary.json",
      "tracked_coverage_pct": 100.0,
      "freshness_coverage_pct": 33.3,
      "disabled_source_classification": {
        "awaiting_url_replacement": 0,
        "awaiting_secret": 2,
        "awaiting_smoke_test": 0,
        "upstream_section_missing": 0,
        "awaiting_partnership_review": 0,
        "accepted_backlog": 0
      },
      "disabled_source_classification_total": 2,
      "collection_errors": 0,
      "freshness_gap": 0,
      "stale_sources": 0,
      "missing_sources": 0,
      "unknown_event_date_sources": 0,
      "disabled_sources": 2,
      "total_sources": 3,
      "enabled_sources": 3,
      "tracked_sources": 3,
      "fresh_sources": 1,
      "not_tracked_sources": 0,
      "operational_priority": "P2",
      "taxonomy_priority": "T1",
      "risk_score": 27,
      "focus_area": "taxonomy_enrichment"
    },
    {
      "repo": "FinanceTaxMCPRadar",
      "display_name": "FinanceTaxMCP",
      "category": "finance_tax_mcp",
      "repo_class": "standard-radar",
      "domain_family": "mcp-financetax",
      "primary_motion": "compliance-risk",
      "governance_profile": "medium",
      "evidence_strategy": "balanced-mixed",
      "readiness_status": "watch",
      "source_status": "л¶Ҳк· нҳ•",
      "available_layers": [
        "community"
      ],
      "missing_layers": [
        "market"
      ],
      "layer_counts": {
        "community": 1
      },
      "next_step": "awesome-mcp-korea community seedлҘј GitHub repository metadataмҷҖ security/risk cross-checkлЎң ліҙк°•н•ңлӢӨ.",
      "quality_score": 80,
      "taxonomy_priority_score": 30,
      "article_count": 5,
      "matched_count": 5,
      "match_rate": 100.0,
      "source_count": 1,
      "dashboard_status": "active",
      "last_updated": "2026-04-24",
      "warnings": [
        "quality report has 2 disabled source(s)"
      ],
      "warning_count": 1,
      "quality_origin": "FinanceTaxMCPRadar/reports/finance_tax_mcp_20260428_quality.json",
      "data_origin": "FinanceTaxMCPRadar/reports/finance_tax_mcp_20260424_summary.json",
      "tracked_coverage_pct": 100.0,
      "freshness_coverage_pct": 33.3,
      "disabled_source_classification": {
        "awaiting_url_replacement": 0,
        "awaiting_secret": 1,
        "awaiting_smoke_test": 1,
        "upstream_section_missing": 0,
        "awaiting_partnership_review": 0,
        "accepted_backlog": 0
      },
      "disabled_source_classification_total": 2,
      "collection_errors": 0,
      "freshness_gap": 0,
      "stale_sources": 0,
      "missing_sources": 0,
      "unknown_event_date_sources": 0,
      "disabled_sources": 2,
      "total_sources": 3,
      "enabled_sources": 3,
      "tracked_sources": 3,
      "fresh_sources": 1,
      "not_tracked_sources": 0,
      "operational_priority": "P2",
      "taxonomy_priority": "T1",
      "risk_score": 27,
      "focus_area": "taxonomy_enrichment"
    },
    {
      "repo": "GameRadar",
      "display_name": "Game",
      "category": "game",
      "repo_class": "standard-radar",
      "domain_family": "games",
      "primary_motion": "intelligence",
      "governance_profile": "low",
      "evidence_strategy": "official-operational",
      "readiness_status": "watch",
      "source_status": "л¶Ҳк· нҳ•",
      "available_layers": [
        "community",
        "market",
        "official",
        "operational"
      ],
      "missing_layers": [],
      "layer_counts": {
        "community": 13,
        "market": 25,
        "official": 2,
        "operational": 4
      },
      "next_step": "Steam charts, app store ranking, мҪҳмҶ” мҠӨнҶ м–ҙ bestseller, patch noteлҘј л„Јм–ҙ нқҘн–ү м¶”м Ғмқ„ ліҙк°•н•ңлӢӨ.",
      "quality_score": 85,
      "taxonomy_priority_score": 22,
      "article_count": 300,
      "matched_count": 300,
      "match_rate": 100.0,
      "source_count": 32,
      "dashboard_status": "active",
      "last_updated": "2026-04-24",
      "warnings": [
        "quality report has 11 disabled source(s)"
      ],
      "warning_count": 1,
      "quality_origin": "GameRadar/reports/game_20260428_quality.json",
      "data_origin": "GameRadar/reports/game_20260424_summary.json",
      "tracked_coverage_pct": 16.2,
      "freshness_coverage_pct": 66.7,
      "disabled_source_classification": {
        "awaiting_url_replacement": 8,
        "awaiting_secret": 0,
        "awaiting_smoke_test": 0,
        "upstream_section_missing": 0,
        "awaiting_partnership_review": 0,
        "accepted_backlog": 3
      },
      "disabled_source_classification_total": 11,
      "collection_errors": 0,
      "freshness_gap": 0,
      "stale_sources": 0,
      "missing_sources": 0,
      "unknown_event_date_sources": 0,
      "disabled_sources": 11,
      "total_sources": 48,
      "enabled_sources": 37,
      "tracked_sources": 6,
      "fresh_sources": 4,
      "not_tracked_sources": 33,
      "operational_priority": "P1",
      "taxonomy_priority": "T1",
      "risk_score": 27,
      "focus_area": "disabled_source_governance"
    },
    {
      "repo": "LegalGovMCPRadar",
      "display_name": "LegalGovMCP",
      "category": "legal_gov_mcp",
      "repo_class": "standard-radar",
      "domain_family": "mcp-legalgov",
      "primary_motion": "compliance-risk",
      "governance_profile": "medium",
      "evidence_strategy": "balanced-mixed",
      "readiness_status": "watch",
      "source_status": "л¶Ҳк· нҳ•",
      "available_layers": [
        "community"
      ],
      "missing_layers": [
        "market"
      ],
      "layer_counts": {
        "community": 1
      },
      "next_step": "awesome-mcp-korea community seedлҘј GitHub repository metadataмҷҖ security/risk cross-checkлЎң ліҙк°•н•ңлӢӨ.",
      "quality_score": 80,
      "taxonomy_priority_score": 30,
      "article_count": 5,
      "matched_count": 5,
      "match_rate": 100.0,
      "source_count": 1,
      "dashboard_status": "active",
      "last_updated": "2026-04-24",
      "warnings": [
        "quality report has 2 disabled source(s)"
      ],
      "warning_count": 1,
      "quality_origin": "LegalGovMCPRadar/reports/legal_gov_mcp_20260428_quality.json",
      "data_origin": "LegalGovMCPRadar/reports/legal_gov_mcp_20260424_summary.json",
      "tracked_coverage_pct": 100.0,
      "freshness_coverage_pct": 33.3,
      "disabled_source_classification": {
        "awaiting_url_replacement": 0,
        "awaiting_secret": 2,
        "awaiting_smoke_test": 0,
        "upstream_section_missing": 0,
        "awaiting_partnership_review": 0,
        "accepted_backlog": 0
      },
      "disabled_source_classification_total": 2,
      "collection_errors": 0,
      "freshness_gap": 0,
      "stale_sources": 0,
      "missing_sources": 0,
      "unknown_event_date_sources": 0,
      "disabled_sources": 2,
      "total_sources": 3,
      "enabled_sources": 3,
      "tracked_sources": 3,
      "fresh_sources": 1,
      "not_tracked_sources": 0,
      "operational_priority": "P2",
      "taxonomy_priority": "T1",
      "risk_score": 27,
      "focus_area": "taxonomy_enrichment"
    },
    {
      "repo": "MapAddressMCPRadar",
      "display_name": "MapAddressMCP",
      "category": "map_address_mcp",
      "repo_class": "standard-radar",
      "domain_family": "mcp-mapaddress",
      "primary_motion": "compliance-risk",
      "governance_profile": "medium",
      "evidence_strategy": "balanced-mixed",
      "readiness_status": "watch",
      "source_status": "л¶Ҳк· нҳ•",
      "available_layers": [
        "community"
      ],
      "missing_layers": [
        "market"
      ],
      "layer_counts": {
        "community": 1
      },
      "next_step": "awesome-mcp-korea community seedлҘј GitHub repository metadataмҷҖ security/risk cross-checkлЎң ліҙк°•н•ңлӢӨ.",
      "quality_score": 80,
      "taxonomy_priority_score": 30,
      "article_count": 6,
      "matched_count": 6,
      "match_rate": 100.0,
      "source_count": 1,
      "dashboard_status": "active",
      "last_updated": "2026-04-24",
      "warnings": [
        "quality report has 2 disabled source(s)"
      ],
      "warning_count": 1,
      "quality_origin": "MapAddressMCPRadar/reports/map_address_mcp_20260428_quality.json",
      "data_origin": "MapAddressMCPRadar/reports/map_address_mcp_20260424_summary.json",
      "tracked_coverage_pct": 100.0,
      "freshness_coverage_pct": 33.3,
      "disabled_source_classification": {
        "awaiting_url_replacement": 0,
        "awaiting_secret": 2,
        "awaiting_smoke_test": 0,
        "upstream_section_missing": 0,
        "awaiting_partnership_review": 0,
        "accepted_backlog": 0
      },
      "disabled_source_classification_total": 2,
      "collection_errors": 0,
      "freshness_gap": 0,
      "stale_sources": 0,
      "missing_sources": 0,
      "unknown_event_date_sources": 0,
      "disabled_sources": 2,
      "total_sources": 3,
      "enabled_sources": 3,
      "tracked_sources": 3,
      "fresh_sources": 1,
      "not_tracked_sources": 0,
      "operational_priority": "P2",
      "taxonomy_priority": "T1",
      "risk_score": 27,
      "focus_area": "taxonomy_enrichment"
    },
    {
      "repo": "MiscMCPRadar",
      "display_name": "MiscMCP",
      "category": "misc_mcp",
      "repo_class": "standard-radar",
      "domain_family": "mcp-misc",
      "primary_motion": "compliance-risk",
      "governance_profile": "medium",
      "evidence_strategy": "balanced-mixed",
      "readiness_status": "upgrade",
      "source_status": "ліҙк°•мҡ°м„ ",
      "available_layers": [],
      "missing_layers": [
        "community",
        "market"
      ],
      "layer_counts": {},
      "next_step": "awesome-mcp-korea community seedлҘј GitHub repository metadataмҷҖ security/risk cross-checkлЎң ліҙк°•н•ңлӢӨ.",
      "quality_score": 70,
      "taxonomy_priority_score": 62,
      "article_count": 0,
      "matched_count": 0,
      "match_rate": 0.0,
      "source_count": 0,
      "dashboard_status": "active",
      "last_updated": "2026-04-24",
      "warnings": [
        "quality report has 1 disabled source(s)"
      ],
      "warning_count": 1,
      "quality_origin": "MiscMCPRadar/reports/misc_mcp_20260428_quality.json",
      "data_origin": "MiscMCPRadar/reports/misc_mcp_20260424_summary.json",
      "tracked_coverage_pct": 100.0,
      "freshness_coverage_pct": 0.0,
      "disabled_source_classification": {
        "awaiting_url_replacement": 0,
        "awaiting_secret": 0,
        "awaiting_smoke_test": 0,
        "upstream_section_missing": 1,
        "awaiting_partnership_review": 0,
        "accepted_backlog": 0
      },
      "disabled_source_classification_total": 1,
      "collection_errors": 0,
      "freshness_gap": 0,
      "stale_sources": 0,
      "missing_sources": 0,
      "unknown_event_date_sources": 0,
      "disabled_sources": 1,
      "total_sources": 1,
      "enabled_sources": 1,
      "tracked_sources": 1,
      "fresh_sources": 0,
      "not_tracked_sources": 0,
      "operational_priority": "P2",
      "taxonomy_priority": "T1",
      "risk_score": 27,
      "focus_area": "taxonomy_enrichment"
    },
    {
      "repo": "PublicDataMCPRadar",
      "display_name": "PublicDataMCP",
      "category": "publicdata_mcp",
      "repo_class": "standard-radar",
      "domain_family": "mcp-publicdata",
      "primary_motion": "compliance-risk",
      "governance_profile": "medium",
      "evidence_strategy": "balanced-mixed",
      "readiness_status": "watch",
      "source_status": "л¶Ҳк· нҳ•",
      "available_layers": [
        "community"
      ],
      "missing_layers": [
        "market"
      ],
      "layer_counts": {
        "community": 1
      },
      "next_step": "awesome-mcp-korea community seedлҘј GitHub repository metadataмҷҖ security/risk cross-checkлЎң ліҙк°•н•ңлӢӨ.",
      "quality_score": 80,
      "taxonomy_priority_score": 30,
      "article_count": 7,
      "matched_count": 7,
      "match_rate": 100.0,
      "source_count": 1,
      "dashboard_status": "active",
      "last_updated": "2026-04-24",
      "warnings": [
        "quality report has 2 disabled source(s)"
      ],
      "warning_count": 1,
      "quality_origin": "PublicDataMCPRadar/reports/publicdata_mcp_20260428_quality.json",
      "data_origin": "PublicDataMCPRadar/reports/publicdata_mcp_20260424_summary.json",
      "tracked_coverage_pct": 100.0,
      "freshness_coverage_pct": 33.3,
      "disabled_source_classification": {
        "awaiting_url_replacement": 0,
        "awaiting_secret": 2,
        "awaiting_smoke_test": 0,
        "upstream_section_missing": 0,
        "awaiting_partnership_review": 0,
        "accepted_backlog": 0
      },
      "disabled_source_classification_total": 2,
      "collection_errors": 0,
      "freshness_gap": 0,
      "stale_sources": 0,
      "missing_sources": 0,
      "unknown_event_date_sources": 0,
      "disabled_sources": 2,
      "total_sources": 3,
      "enabled_sources": 3,
      "tracked_sources": 3,
      "fresh_sources": 1,
      "not_tracked_sources": 0,
      "operational_priority": "P2",
      "taxonomy_priority": "T1",
      "risk_score": 27,
      "focus_area": "taxonomy_enrichment"
    },
    {
      "repo": "SearchTrendMCPRadar",
      "display_name": "SearchTrendMCP",
      "category": "search_trend_mcp",
      "repo_class": "standard-radar",
      "domain_family": "mcp-searchtrend",
      "primary_motion": "compliance-risk",
      "governance_profile": "medium",
      "evidence_strategy": "balanced-mixed",
      "readiness_status": "watch",
      "source_status": "л¶Ҳк· нҳ•",
      "available_layers": [
        "community"
      ],
      "missing_layers": [
        "market"
      ],
      "layer_counts": {
        "community": 1
      },
      "next_step": "awesome-mcp-korea community seedлҘј GitHub repository metadataмҷҖ security/risk cross-checkлЎң ліҙк°•н•ңлӢӨ.",
      "quality_score": 80,
      "taxonomy_priority_score": 30,
      "article_count": 2,
      "matched_count": 2,
      "match_rate": 100.0,
      "source_count": 1,
      "dashboard_status": "active",
      "last_updated": "2026-04-24",
      "warnings": [
        "quality report has 2 disabled source(s)"
      ],
      "warning_count": 1,
      "quality_origin": "SearchTrendMCPRadar/reports/search_trend_mcp_20260428_quality.json",
      "data_origin": "SearchTrendMCPRadar/reports/search_trend_mcp_20260424_summary.json",
      "tracked_coverage_pct": 100.0,
      "freshness_coverage_pct": 33.3,
      "disabled_source_classification": {
        "awaiting_url_replacement": 0,
        "awaiting_secret": 2,
        "awaiting_smoke_test": 0,
        "upstream_section_missing": 0,
        "awaiting_partnership_review": 0,
        "accepted_backlog": 0
      },
      "disabled_source_classification_total": 2,
      "collection_errors": 0,
      "freshness_gap": 0,
      "stale_sources": 0,
      "missing_sources": 0,
      "unknown_event_date_sources": 0,
      "disabled_sources": 2,
      "total_sources": 3,
      "enabled_sources": 3,
      "tracked_sources": 3,
      "fresh_sources": 1,
      "not_tracked_sources": 0,
      "operational_priority": "P2",
      "taxonomy_priority": "T1",
      "risk_score": 27,
      "focus_area": "taxonomy_enrichment"
    },
    {
      "repo": "TravelMCPRadar",
      "display_name": "TravelMCP",
      "category": "travel_mcp",
      "repo_class": "standard-radar",
      "domain_family": "mcp-travel",
      "primary_motion": "compliance-risk",
      "governance_profile": "medium",
      "evidence_strategy": "balanced-mixed",
      "readiness_status": "watch",
      "source_status": "л¶Ҳк· нҳ•",
      "available_layers": [
        "community"
      ],
      "missing_layers": [
        "market"
      ],
      "layer_counts": {
        "community": 1
      },
      "next_step": "awesome-mcp-korea community seedлҘј GitHub repository metadataмҷҖ security/risk cross-checkлЎң ліҙк°•н•ңлӢӨ.",
      "quality_score": 80,
      "taxonomy_priority_score": 30,
      "article_count": 2,
      "matched_count": 2,
      "match_rate": 100.0,
      "source_count": 1,
      "dashboard_status": "active",
      "last_updated": "2026-04-24",
      "warnings": [
        "quality report has 2 disabled source(s)"
      ],
      "warning_count": 1,
      "quality_origin": "TravelMCPRadar/reports/travel_mcp_20260428_quality.json",
      "data_origin": "TravelMCPRadar/reports/travel_mcp_20260424_summary.json",
      "tracked_coverage_pct": 100.0,
      "freshness_coverage_pct": 33.3,
      "disabled_source_classification": {
        "awaiting_url_replacement": 0,
        "awaiting_secret": 2,
        "awaiting_smoke_test": 0,
        "upstream_section_missing": 0,
        "awaiting_partnership_review": 0,
        "accepted_backlog": 0
      },
      "disabled_source_classification_total": 2,
      "collection_errors": 0,
      "freshness_gap": 0,
      "stale_sources": 0,
      "missing_sources": 0,
      "unknown_event_date_sources": 0,
      "disabled_sources": 2,
      "total_sources": 3,
      "enabled_sources": 3,
      "tracked_sources": 3,
      "fresh_sources": 1,
      "not_tracked_sources": 0,
      "operational_priority": "P2",
      "taxonomy_priority": "T1",
      "risk_score": 27,
      "focus_area": "taxonomy_enrichment"
    },
    {
      "repo": "WeatherMCPRadar",
      "display_name": "WeatherMCP",
      "category": "weather_mcp",
      "repo_class": "standard-radar",
      "domain_family": "mcp-weather",
      "primary_motion": "compliance-risk",
      "governance_profile": "medium",
      "evidence_strategy": "balanced-mixed",
      "readiness_status": "watch",
      "source_status": "л¶Ҳк· нҳ•",
      "available_layers": [
        "community"
      ],
      "missing_layers": [
        "market"
      ],
      "layer_counts": {
        "community": 1
      },
      "next_step": "awesome-mcp-korea community seedлҘј GitHub repository metadataмҷҖ security/risk cross-checkлЎң ліҙк°•н•ңлӢӨ.",
      "quality_score": 80,
      "taxonomy_priority_score": 30,
      "article_count": 5,
      "matched_count": 5,
      "match_rate": 100.0,
      "source_count": 1,
      "dashboard_status": "active",
      "last_updated": "2026-04-24",
      "warnings": [
        "quality report has 2 disabled source(s)"
      ],
      "warning_count": 1,
      "quality_origin": "WeatherMCPRadar/reports/weather_mcp_20260428_quality.json",
      "data_origin": "WeatherMCPRadar/reports/weather_mcp_20260424_summary.json",
      "tracked_coverage_pct": 100.0,
      "freshness_coverage_pct": 33.3,
      "disabled_source_classification": {
        "awaiting_url_replacement": 0,
        "awaiting_secret": 2,
        "awaiting_smoke_test": 0,
        "upstream_section_missing": 0,
        "awaiting_partnership_review": 0,
        "accepted_backlog": 0
      },
      "disabled_source_classification_total": 2,
      "collection_errors": 0,
      "freshness_gap": 0,
      "stale_sources": 0,
      "missing_sources": 0,
      "unknown_event_date_sources": 0,
      "disabled_sources": 2,
      "total_sources": 3,
      "enabled_sources": 3,
      "tracked_sources": 3,
      "fresh_sources": 1,
      "not_tracked_sources": 0,
      "operational_priority": "P2",
      "taxonomy_priority": "T1",
      "risk_score": 27,
      "focus_area": "taxonomy_enrichment"
    },
    {
      "repo": "BenefitRadar",
      "display_name": "Benefit",
      "category": "benefit",
      "repo_class": "standard-radar",
      "domain_family": "public-benefits",
      "primary_motion": "conversion",
      "governance_profile": "medium",
      "evidence_strategy": "official-operational",
      "readiness_status": "watch",
      "source_status": "л¶Ҳк· нҳ•",
      "available_layers": [
        "community",
        "market",
        "official",
        "operational"
      ],
      "missing_layers": [],
      "layer_counts": {
        "community": 8,
        "market": 22,
        "official": 15,
        "operational": 11
      },
      "next_step": "мӢ мІӯ л§Ҳк°җмқј, eligibility кі„мӮ°, м§‘н–ү мӢӨм Ғк№Ңм§Җ л¶ҷм—¬ мӢӨм ң мӢ мІӯ н–үлҸҷкіј м—°кІ°н•ңлӢӨ.",
      "quality_score": 85,
      "taxonomy_priority_score": 26,
      "article_count": 290,
      "matched_count": 290,
      "match_rate": 100.0,
      "source_count": 22,
      "dashboard_status": "active",
      "last_updated": "2026-04-25",
      "warnings": [
        "quality freshness gaps: stale=5, missing=0, unknown_event_date=0",
        "quality report has 8 disabled source(s)"
      ],
      "warning_count": 2,
      "quality_origin": "BenefitRadar/reports/benefit_20260428_quality.json",
      "data_origin": "BenefitRadar/reports/benefit_20260425_summary.json",
      "tracked_coverage_pct": 36.7,
      "freshness_coverage_pct": 54.5,
      "disabled_source_classification": {
        "awaiting_url_replacement": 6,
        "awaiting_secret": 0,
        "awaiting_smoke_test": 0,
        "upstream_section_missing": 0,
        "awaiting_partnership_review": 0,
        "accepted_backlog": 2
      },
      "disabled_source_classification_total": 8,
      "collection_errors": 0,
      "freshness_gap": 5,
      "stale_sources": 5,
      "missing_sources": 0,
      "unknown_event_date_sources": 0,
      "disabled_sources": 8,
      "total_sources": 38,
      "enabled_sources": 30,
      "tracked_sources": 11,
      "fresh_sources": 6,
      "not_tracked_sources": 19,
      "operational_priority": "P1",
      "taxonomy_priority": "T1",
      "risk_score": 26,
      "focus_area": "freshness_coverage"
    },
    {
      "repo": "KoreanNLPMCPRadar",
      "display_name": "KoreanNLPMCP",
      "category": "korean_nlp_mcp",
      "repo_class": "standard-radar",
      "domain_family": "mcp-koreannlp",
      "primary_motion": "compliance-risk",
      "governance_profile": "medium",
      "evidence_strategy": "balanced-mixed",
      "readiness_status": "watch",
      "source_status": "л¶Ҳк· нҳ•",
      "available_layers": [
        "community"
      ],
      "missing_layers": [
        "market"
      ],
      "layer_counts": {
        "community": 2
      },
      "next_step": "awesome-mcp-korea community seedлҘј GitHub repository metadataмҷҖ security/risk cross-checkлЎң ліҙк°•н•ңлӢӨ.",
      "quality_score": 80,
      "taxonomy_priority_score": 30,
      "article_count": 3,
      "matched_count": 3,
      "match_rate": 100.0,
      "source_count": 2,
      "dashboard_status": "active",
      "last_updated": "2026-04-24",
      "warnings": [
        "quality report has 1 disabled source(s)"
      ],
      "warning_count": 1,
      "quality_origin": "KoreanNLPMCPRadar/reports/korean_nlp_mcp_20260428_quality.json",
      "data_origin": "KoreanNLPMCPRadar/reports/korean_nlp_mcp_20260424_summary.json",
      "tracked_coverage_pct": 100.0,
      "freshness_coverage_pct": 66.7,
      "disabled_source_classification": {
        "awaiting_url_replacement": 0,
        "awaiting_secret": 0,
        "awaiting_smoke_test": 1,
        "upstream_section_missing": 0,
        "awaiting_partnership_review": 0,
        "accepted_backlog": 0
      },
      "disabled_source_classification_total": 1,
      "collection_errors": 0,
      "freshness_gap": 0,
      "stale_sources": 0,
      "missing_sources": 0,
      "unknown_event_date_sources": 0,
      "disabled_sources": 1,
      "total_sources": 3,
      "enabled_sources": 3,
      "tracked_sources": 3,
      "fresh_sources": 2,
      "not_tracked_sources": 0,
      "operational_priority": "P2",
      "taxonomy_priority": "T1",
      "risk_score": 26,
      "focus_area": "taxonomy_enrichment"
    },
    {
      "repo": "RealEstateMCPRadar",
      "display_name": "RealEstateMCP",
      "category": "realestate_mcp",
      "repo_class": "standard-radar",
      "domain_family": "mcp-realestate",
      "primary_motion": "compliance-risk",
      "governance_profile": "medium",
      "evidence_strategy": "balanced-mixed",
      "readiness_status": "watch",
      "source_status": "л¶Ҳк· нҳ•",
      "available_layers": [
        "community"
      ],
      "missing_layers": [
        "market"
      ],
      "layer_counts": {
        "community": 1
      },
      "next_step": "awesome-mcp-korea community seedлҘј GitHub repository metadataмҷҖ security/risk cross-checkлЎң ліҙк°•н•ңлӢӨ.",
      "quality_score": 80,
      "taxonomy_priority_score": 30,
      "article_count": 3,
      "matched_count": 3,
      "match_rate": 100.0,
      "source_count": 1,
      "dashboard_status": "active",
      "last_updated": "2026-04-24",
      "warnings": [
        "quality report has 1 disabled source(s)"
      ],
      "warning_count": 1,
      "quality_origin": "RealEstateMCPRadar/reports/realestate_mcp_20260428_quality.json",
      "data_origin": "RealEstateMCPRadar/reports/realestate_mcp_20260424_summary.json",
      "tracked_coverage_pct": 100.0,
      "freshness_coverage_pct": 50.0,
      "disabled_source_classification": {
        "awaiting_url_replacement": 0,
        "awaiting_secret": 1,
        "awaiting_smoke_test": 0,
        "upstream_section_missing": 0,
        "awaiting_partnership_review": 0,
        "accepted_backlog": 0
      },
      "disabled_source_classification_total": 1,
      "collection_errors": 0,
      "freshness_gap": 0,
      "stale_sources": 0,
      "missing_sources": 0,
      "unknown_event_date_sources": 0,
      "disabled_sources": 1,
      "total_sources": 2,
      "enabled_sources": 2,
      "tracked_sources": 2,
      "fresh_sources": 1,
      "not_tracked_sources": 0,
      "operational_priority": "P2",
      "taxonomy_priority": "T1",
      "risk_score": 26,
      "focus_area": "taxonomy_enrichment"
    },
    {
      "repo": "EventRadar",
      "display_name": "Event",
      "category": "event",
      "repo_class": "standard-radar",
      "domain_family": "events",
      "primary_motion": "intelligence",
      "governance_profile": "medium",
      "evidence_strategy": "official-operational",
      "readiness_status": "watch",
      "source_status": "л¶Ҳк· нҳ•",
      "available_layers": [
        "community",
        "market",
        "official",
        "operational"
      ],
      "missing_layers": [],
      "layer_counts": {
        "community": 4,
        "market": 28,
        "official": 6,
        "operational": 1
      },
      "next_step": "кіөмӢқ мқјм • API, нӢ°мј“ нҢҗл§ӨВ·мһ”м—¬м„қ, venue calendarлҘј л¶ҷм—¬ мӢӨн–ү к°ҖлҠҘм„ұмқ„ лҶ’мқёлӢӨ.",
      "quality_score": 85,
      "taxonomy_priority_score": 26,
      "article_count": 383,
      "matched_count": 383,
      "match_rate": 100.0,
      "source_count": 26,
      "dashboard_status": "active",
      "last_updated": "2026-04-25",
      "warnings": [
        "quality freshness gaps: stale=5, missing=0, unknown_event_date=0",
        "quality report has 8 disabled source(s)"
      ],
      "warning_count": 2,
      "quality_origin": "EventRadar/reports/event_20260428_quality.json",
      "data_origin": "EventRadar/reports/event_20260425_summary.json",
      "tracked_coverage_pct": 60.7,
      "freshness_coverage_pct": 70.6,
      "disabled_source_classification": {
        "awaiting_url_replacement": 2,
        "awaiting_secret": 0,
        "awaiting_smoke_test": 0,
        "upstream_section_missing": 0,
        "awaiting_partnership_review": 0,
        "accepted_backlog": 6
      },
      "disabled_source_classification_total": 8,
      "collection_errors": 0,
      "freshness_gap": 5,
      "stale_sources": 5,
      "missing_sources": 0,
      "unknown_event_date_sources": 0,
      "disabled_sources": 8,
      "total_sources": 36,
      "enabled_sources": 28,
      "tracked_sources": 17,
      "fresh_sources": 12,
      "not_tracked_sources": 11,
      "operational_priority": "P1",
      "taxonomy_priority": "T1",
      "risk_score": 25,
      "focus_area": "freshness_coverage"
    },
    {
      "repo": "HomeRadar",
      "display_name": "Home",
      "category": "home",
      "repo_class": "advanced-radar",
      "domain_family": "housing",
      "primary_motion": "conversion",
      "governance_profile": "high",
      "evidence_strategy": "official-operational",
      "readiness_status": "ready",
      "source_status": "к°•н•Ё",
      "available_layers": [
        "market",
        "official",
        "operational"
      ],
      "missing_layers": [],
      "layer_counts": {
        "market": 6,
        "official": 6,
        "operational": 5
      },
      "next_step": "HomeVerificationStateлҘј лҰ¬нҸ¬нҠё/MCP м¶ңл Ҙм—җ м—°кІ°н•ҳкі  listingВ·мһ¬кі  нӣ„ліҙлҠ” ToSВ·stale listing кІҖмҰқ нӣ„ лӢЁкі„м ҒмңјлЎң нҷңм„ұнҷ”н•ңлӢӨ.",
      "quality_score": 95,
      "taxonomy_priority_score": 14,
      "article_count": 100,
      "matched_count": 77,
      "match_rate": 77.0,
      "source_count": 3,
      "dashboard_status": "active",
      "last_updated": "2026-04-24",
      "warnings": [
        "official primary HomeRadar sources blocked by missing env (molit_apt_transaction, molit_apt_rent, reb_subscription, onbid_auction; required: MOLIT_SERVICE_KEY, ONBID_API_KEY, SUBSCRIPTION_API_KEY)",
        "quality report has 15 disabled source(s)"
      ],
      "warning_count": 2,
      "quality_origin": "HomeRadar/reports/home_20260428_quality.json",
      "data_origin": "HomeRadar/reports/home_20260424_summary.json",
      "tracked_coverage_pct": 40.0,
      "freshness_coverage_pct": 0.0,
      "disabled_source_classification": {
        "awaiting_url_replacement": 2,
        "awaiting_secret": 0,
        "awaiting_smoke_test": 0,
        "upstream_section_missing": 0,
        "awaiting_partnership_review": 0,
        "accepted_backlog": 13
      },
      "disabled_source_classification_total": 15,
      "collection_errors": 0,
      "freshness_gap": 0,
      "stale_sources": 0,
      "missing_sources": 0,
      "unknown_event_date_sources": 0,
      "disabled_sources": 15,
      "total_sources": 25,
      "enabled_sources": 10,
      "tracked_sources": 4,
      "fresh_sources": 0,
      "not_tracked_sources": 6,
      "operational_priority": "P0",
      "taxonomy_priority": "T3",
      "risk_score": 24,
      "focus_area": "collector_repair"
    },
    {
      "repo": "SubscriptionRadar",
      "display_name": "Subscription",
      "category": "subscription",
      "repo_class": "standard-radar",
      "domain_family": "subscription-pricing",
      "primary_motion": "conversion",
      "governance_profile": "medium",
      "evidence_strategy": "official-operational",
      "readiness_status": "watch",
      "source_status": "л¶Ҳк· нҳ•",
      "available_layers": [
        "market",
        "official",
        "operational"
      ],
      "missing_layers": [],
      "layer_counts": {
        "market": 35,
        "official": 15,
        "operational": 11
      },
      "next_step": "vendor pricing page, app store ranking, churn signal, м№ҙл“ң кІ°м ң м№ҙн…Ңкі лҰ¬ лҚ°мқҙн„°лҘј лҚ”н•ңлӢӨ.",
      "quality_score": 85,
      "taxonomy_priority_score": 26,
      "article_count": 70,
      "matched_count": 70,
      "match_rate": 100.0,
      "source_count": 23,
      "dashboard_status": "active",
      "last_updated": "2026-04-25",
      "warnings": [
        "quality freshness gaps: stale=1, missing=0, unknown_event_date=0",
        "quality report has 14 disabled source(s)"
      ],
      "warning_count": 2,
      "quality_origin": "SubscriptionRadar/reports/subscription_20260428_quality.json",
      "data_origin": "SubscriptionRadar/reports/subscription_20260425_summary.json",
      "tracked_coverage_pct": 67.6,
      "freshness_coverage_pct": 44.0,
      "disabled_source_classification": {
        "awaiting_url_replacement": 0,
        "awaiting_secret": 0,
        "awaiting_smoke_test": 0,
        "upstream_section_missing": 0,
        "awaiting_partnership_review": 0,
        "accepted_backlog": 14
      },
      "disabled_source_classification_total": 14,
      "collection_errors": 0,
      "freshness_gap": 1,
      "stale_sources": 1,
      "missing_sources": 0,
      "unknown_event_date_sources": 0,
      "disabled_sources": 14,
      "total_sources": 51,
      "enabled_sources": 37,
      "tracked_sources": 25,
      "fresh_sources": 11,
      "not_tracked_sources": 21,
      "operational_priority": "P1",
      "taxonomy_priority": "T1",
      "risk_score": 24,
      "focus_area": "disabled_source_governance"
    },
    {
      "repo": "GovRadar",
      "display_name": "Gov",
      "category": "govsupport",
      "repo_class": "standard-radar",
      "domain_family": "public-programs",
      "primary_motion": "conversion",
      "governance_profile": "high",
      "evidence_strategy": "official-operational",
      "readiness_status": "watch",
      "source_status": "л¶Ҳк· нҳ•",
      "available_layers": [
        "community",
        "market",
        "official",
        "operational"
      ],
      "missing_layers": [],
      "layer_counts": {
        "community": 5,
        "market": 24,
        "official": 7,
        "operational": 8
      },
      "next_step": "application_deadlineВ·eligibility_rule мқҙлІӨнҠё лӘЁлҚёмқ„ мӨ‘мӢ¬мңјлЎң freshness/stale лҰ¬нҸ¬нҠёлҘј л¶ҷмқҙкі , м„ м • кІ°кіјВ·м§‘н–ү мӢӨм Ғ нӣ„ліҙлҠ” source_backlogм—җм„ң кІҖмҰқ нӣ„ лӢЁкі„м ҒмңјлЎң нҷңм„ұнҷ”н•ңлӢӨ.",
      "quality_score": 85,
      "taxonomy_priority_score": 32,
      "article_count": 74,
      "matched_count": 74,
      "match_rate": 100.0,
      "source_count": 14,
      "dashboard_status": "active",
      "last_updated": "2026-04-25",
      "warnings": [
        "quality freshness gaps: stale=5, missing=0, unknown_event_date=0",
        "quality report has 1 disabled source(s)"
      ],
      "warning_count": 2,
      "quality_origin": "GovRadar/reports/govsupport_20260428_quality.json",
      "data_origin": "GovRadar/reports/govsupport_20260425_summary.json",
      "tracked_coverage_pct": 25.0,
      "freshness_coverage_pct": 16.7,
      "disabled_source_classification": {
        "awaiting_url_replacement": 0,
        "awaiting_secret": 0,
        "awaiting_smoke_test": 0,
        "upstream_section_missing": 0,
        "awaiting_partnership_review": 0,
        "accepted_backlog": 1
      },
      "disabled_source_classification_total": 1,
      "collection_errors": 0,
      "freshness_gap": 5,
      "stale_sources": 5,
      "missing_sources": 0,
      "unknown_event_date_sources": 0,
      "disabled_sources": 1,
      "total_sources": 25,
      "enabled_sources": 24,
      "tracked_sources": 6,
      "fresh_sources": 1,
      "not_tracked_sources": 18,
      "operational_priority": "P1",
      "taxonomy_priority": "T1",
      "risk_score": 23,
      "focus_area": "freshness_coverage"
    },
    {
      "repo": "JobRadar",
      "display_name": "Job",
      "category": "job",
      "repo_class": "standard-radar",
      "domain_family": "employment",
      "primary_motion": "conversion",
      "governance_profile": "high",
      "evidence_strategy": "official-operational",
      "readiness_status": "watch",
      "source_status": "л¶Ҳк· нҳ•",
      "available_layers": [
        "community",
        "market",
        "official",
        "operational"
      ],
      "missing_layers": [],
      "layer_counts": {
        "community": 7,
        "market": 15,
        "official": 2,
        "operational": 2
      },
      "next_step": "кіөмӢқ мұ„мҡ©кіөкі , job board API, salaryВ·skill trend лҚ°мқҙн„°лҘј лҚ”н•ҙ мҡҙмҳҒ мӢ нҳёлҘј л§Ңл“ лӢӨ.",
      "quality_score": 85,
      "taxonomy_priority_score": 32,
      "article_count": 193,
      "matched_count": 193,
      "match_rate": 100.0,
      "source_count": 15,
      "dashboard_status": "active",
      "last_updated": "2026-04-25",
      "warnings": [
        "quality report has 6 disabled source(s)"
      ],
      "warning_count": 1,
      "quality_origin": "JobRadar/reports/job_20260428_quality.json",
      "data_origin": "JobRadar/reports/job_20260425_summary.json",
      "tracked_coverage_pct": 20.0,
      "freshness_coverage_pct": 100.0,
      "disabled_source_classification": {
        "awaiting_url_replacement": 0,
        "awaiting_secret": 0,
        "awaiting_smoke_test": 0,
        "upstream_section_missing": 0,
        "awaiting_partnership_review": 0,
        "accepted_backlog": 6
      },
      "disabled_source_classification_total": 6,
      "collection_errors": 0,
      "freshness_gap": 0,
      "stale_sources": 0,
      "missing_sources": 0,
      "unknown_event_date_sources": 0,
      "disabled_sources": 6,
      "total_sources": 21,
      "enabled_sources": 15,
      "tracked_sources": 3,
      "fresh_sources": 3,
      "not_tracked_sources": 12,
      "operational_priority": "P2",
      "taxonomy_priority": "T1",
      "risk_score": 21,
      "focus_area": "disabled_source_governance"
    },
    {
      "repo": "CommerceRadar",
      "display_name": "Commerce",
      "category": null,
      "repo_class": "advanced-radar",
      "domain_family": "b2b-commerce-kg",
      "primary_motion": "conversion",
      "governance_profile": "medium",
      "evidence_strategy": "official-operational",
      "readiness_status": "watch",
      "source_status": "к°•н•Ё",
      "available_layers": [
        "attention",
        "market",
        "official",
        "operational"
      ],
      "missing_layers": [],
      "layer_counts": {
        "attention": 1,
        "market": 2,
        "official": 7,
        "operational": 5
      },
      "next_step": "config/sources.yamlмҷҖ schemasлҘј мӢӨм ң мҲҳм§‘/кІҖмҰқ нҢҢмқҙн”„лқјмқём—җ м—°кІ°н•ҳкі  combo card evidence coverageлҘј dashboardм—җ л…ём¶ңн•ңлӢӨ.",
      "quality_score": 65,
      "taxonomy_priority_score": 18,
      "article_count": 0,
      "matched_count": 0,
      "match_rate": null,
      "source_count": 0,
      "dashboard_status": "missing_reports",
      "last_updated": null,
      "warnings": [
        "no dashboard-readable report artifacts found"
      ],
      "warning_count": 1,
      "quality_origin": null,
      "data_origin": null,
      "tracked_coverage_pct": null,
      "freshness_coverage_pct": null,
      "disabled_source_classification": {},
      "disabled_source_classification_total": 0,
      "collection_errors": 0,
      "freshness_gap": 0,
      "stale_sources": 0,
      "missing_sources": 0,
      "unknown_event_date_sources": 0,
      "disabled_sources": 0,
      "total_sources": 0,
      "enabled_sources": 0,
      "tracked_sources": 0,
      "fresh_sources": 0,
      "not_tracked_sources": 0,
      "operational_priority": "P3",
      "taxonomy_priority": "T1",
      "risk_score": 18,
      "focus_area": "taxonomy_enrichment"
    },
    {
      "repo": "PaperRadar",
      "display_name": "Paper",
      "category": "research",
      "repo_class": "standard-radar",
      "domain_family": "ai-research",
      "primary_motion": "intelligence",
      "governance_profile": "low",
      "evidence_strategy": "official-operational",
      "readiness_status": "ready",
      "source_status": "к°•н•Ё",
      "available_layers": [
        "market",
        "official",
        "operational"
      ],
      "missing_layers": [],
      "layer_counts": {
        "market": 18,
        "official": 7,
        "operational": 3
      },
      "next_step": "citation, GitHub star, benchmark leaderboard, мҪ”л“ң м ҖмһҘмҶҢ м—°кІ°мқ„ ліҙк°•н•ңлӢӨ.",
      "quality_score": 95,
      "taxonomy_priority_score": 0,
      "article_count": 54,
      "matched_count": 52,
      "match_rate": 96.3,
      "source_count": 11,
      "dashboard_status": "active",
      "last_updated": "2026-04-25",
      "warnings": [
        "quality freshness gaps: stale=8, missing=0, unknown_event_date=0",
        "quality report has 4 disabled source(s)"
      ],
      "warning_count": 2,
      "quality_origin": "PaperRadar/reports/research_20260428_quality.json",
      "data_origin": "PaperRadar/reports/research_20260425_summary.json",
      "tracked_coverage_pct": 73.7,
      "freshness_coverage_pct": 14.3,
      "disabled_source_classification": {
        "awaiting_url_replacement": 0,
        "awaiting_secret": 0,
        "awaiting_smoke_test": 0,
        "upstream_section_missing": 0,
        "awaiting_partnership_review": 0,
        "accepted_backlog": 4
      },
      "disabled_source_classification_total": 4,
      "collection_errors": 0,
      "freshness_gap": 8,
      "stale_sources": 8,
      "missing_sources": 0,
      "unknown_event_date_sources": 0,
      "disabled_sources": 4,
      "total_sources": 23,
      "enabled_sources": 19,
      "tracked_sources": 14,
      "fresh_sources": 2,
      "not_tracked_sources": 9,
      "operational_priority": "P1",
      "taxonomy_priority": "T3",
      "risk_score": 18,
      "focus_area": "freshness_coverage"
    },
    {
      "repo": "FoodRadar",
      "display_name": "Food",
      "category": "food",
      "repo_class": "standard-radar",
      "domain_family": "food-safety",
      "primary_motion": "compliance-risk",
      "governance_profile": "high",
      "evidence_strategy": "official-operational",
      "readiness_status": "ready",
      "source_status": "к°•н•Ё",
      "available_layers": [
        "community",
        "market",
        "official",
        "operational"
      ],
      "missing_layers": [],
      "layer_counts": {
        "community": 4,
        "market": 7,
        "official": 5,
        "operational": 8
      },
      "next_step": "source_backlogмқҳ мҶҢл№„мһҗ л¶Ҳл§Ң нӣ„ліҙлҘј APIВ·ToSВ·к°ңмқём •ліҙ кІҖнҶ  нӣ„ ліҙмЎ° кІҖмҰқ л Ҳмқҙм–ҙлЎң нҷңм„ұнҷ”н•ҳкі , нҢҗл§ӨмӨ‘лӢЁ нҷ•мӮ°В·мң нҶө к°ҖкІ© лҚ°мқҙн„°лҘј нӣ„мҶҚ мҡҙмҳҒ sourceлЎң ліҙк°•н•ңлӢӨ.",
      "quality_score": 95,
      "taxonomy_priority_score": 10,
      "article_count": 200,
      "matched_count": 163,
      "match_rate": 81.5,
      "source_count": 10,
      "dashboard_status": "active",
      "last_updated": "2026-04-25",
      "warnings": [
        "quality freshness gaps: stale=2, missing=0, unknown_event_date=0",
        "quality report has 1 disabled source(s)"
      ],
      "warning_count": 2,
      "quality_origin": "FoodRadar/reports/food_20260428_quality.json",
      "data_origin": "FoodRadar/reports/food_20260425_summary.json",
      "tracked_coverage_pct": 27.3,
      "freshness_coverage_pct": 33.3,
      "disabled_source_classification": {
        "awaiting_url_replacement": 0,
        "awaiting_secret": 0,
        "awaiting_smoke_test": 0,
        "upstream_section_missing": 0,
        "awaiting_partnership_review": 0,
        "accepted_backlog": 1
      },
      "disabled_source_classification_total": 1,
      "collection_errors": 0,
      "freshness_gap": 2,
      "stale_sources": 2,
      "missing_sources": 0,
      "unknown_event_date_sources": 0,
      "disabled_sources": 1,
      "total_sources": 12,
      "enabled_sources": 11,
      "tracked_sources": 3,
      "fresh_sources": 1,
      "not_tracked_sources": 8,
      "operational_priority": "P0",
      "taxonomy_priority": "T3",
      "risk_score": 16,
      "focus_area": "collector_repair"
    },
    {
      "repo": "CryptoRadar",
      "display_name": "Crypto",
      "category": "crypto",
      "repo_class": "standard-radar",
      "domain_family": "crypto-finance",
      "primary_motion": "intelligence",
      "governance_profile": "medium",
      "evidence_strategy": "official-operational",
      "readiness_status": "ready",
      "source_status": "к°•н•Ё",
      "available_layers": [
        "market",
        "official",
        "operational"
      ],
      "missing_layers": [],
      "layer_counts": {
        "market": 19,
        "official": 5,
        "operational": 5
      },
      "next_step": "кұ°лһҳмҶҢ мғҒмһҘВ·мғҒнҸҗ кіөм§Җ, к·ңм ңкё°кҙҖ л°ңн‘ң, мҳЁмІҙмқё м§Җн‘ңлҘј м¶”к°Җн•ҙ нҲ¬мһҗ нҢҗлӢЁл Ҙмқ„ лҶ’мқёлӢӨ.",
      "quality_score": 95,
      "taxonomy_priority_score": 4,
      "article_count": 200,
      "matched_count": 194,
      "match_rate": 97.0,
      "source_count": 10,
      "dashboard_status": "active",
      "last_updated": "2026-04-25",
      "warnings": [
        "quality freshness gaps: stale=1, missing=0, unknown_event_date=0"
      ],
      "warning_count": 1,
      "quality_origin": "CryptoRadar/reports/crypto_20260428_quality.json",
      "data_origin": "CryptoRadar/reports/crypto_20260425_summary.json",
      "tracked_coverage_pct": 5.3,
      "freshness_coverage_pct": 0.0,
      "disabled_source_classification": {
        "awaiting_url_replacement": 0,
        "awaiting_secret": 0,
        "awaiting_smoke_test": 0,
        "upstream_section_missing": 0,
        "awaiting_partnership_review": 0,
        "accepted_backlog": 0
      },
      "disabled_source_classification_total": 0,
      "collection_errors": 0,
      "freshness_gap": 1,
      "stale_sources": 1,
      "missing_sources": 0,
      "unknown_event_date_sources": 0,
      "disabled_sources": 0,
      "total_sources": 19,
      "enabled_sources": 19,
      "tracked_sources": 1,
      "fresh_sources": 0,
      "not_tracked_sources": 18,
      "operational_priority": "P2",
      "taxonomy_priority": "T3",
      "risk_score": 13,
      "focus_area": "tracked_source_coverage"
    },
    {
      "repo": "MobilityRadar",
      "display_name": "Mobility",
      "category": "mobility",
      "repo_class": "standard-radar",
      "domain_family": "mobility",
      "primary_motion": "intelligence",
      "governance_profile": "medium",
      "evidence_strategy": "official-operational",
      "readiness_status": "ready",
      "source_status": "к°•н•Ё",
      "available_layers": [
        "community",
        "market",
        "official",
        "operational"
      ],
      "missing_layers": [],
      "layer_counts": {
        "community": 7,
        "market": 26,
        "official": 2,
        "operational": 2
      },
      "next_step": "EV л“ұлЎқВ·м¶©м „ мҡ”кёҲВ·лҢҖмӨ‘көҗнҶө мҡ”кёҲ sourceлҘј м¶”к°Җн•ҳкі  coffee split нӣ„ліҙмқҳ лі„лҸ„ repo мҠ№кІ© м—¬л¶ҖлҘј кІ°м •н•ңлӢӨ.",
      "quality_score": 95,
      "taxonomy_priority_score": 4,
      "article_count": 112,
      "matched_count": 112,
      "match_rate": 100.0,
      "source_count": 16,
      "dashboard_status": "active",
      "last_updated": "2026-04-25",
      "warnings": [
        "quality freshness gaps: stale=1, missing=0, unknown_event_date=0",
        "quality report has 5 disabled source(s)"
      ],
      "warning_count": 2,
      "quality_origin": "MobilityRadar/reports/mobility_20260428_quality.json",
      "data_origin": "MobilityRadar/reports/mobility_20260425_summary.json",
      "tracked_coverage_pct": 16.7,
      "freshness_coverage_pct": 25.0,
      "disabled_source_classification": {
        "awaiting_url_replacement": 4,
        "awaiting_secret": 0,
        "awaiting_smoke_test": 0,
        "upstream_section_missing": 0,
        "awaiting_partnership_review": 0,
        "accepted_backlog": 1
      },
      "disabled_source_classification_total": 5,
      "collection_errors": 0,
      "freshness_gap": 1,
      "stale_sources": 1,
      "missing_sources": 0,
      "unknown_event_date_sources": 0,
      "disabled_sources": 5,
      "total_sources": 29,
      "enabled_sources": 24,
      "tracked_sources": 4,
      "fresh_sources": 1,
      "not_tracked_sources": 22,
      "operational_priority": "P2",
      "taxonomy_priority": "T3",
      "risk_score": 13,
      "focus_area": "disabled_source_governance"
    },
    {
      "repo": "BlogRadar",
      "display_name": "Blog",
      "category": "techblog",
      "repo_class": "standard-radar",
      "domain_family": "developer-ecosystem",
      "primary_motion": "intelligence",
      "governance_profile": "low",
      "evidence_strategy": "official-operational",
      "readiness_status": "ready",
      "source_status": "к°•н•Ё",
      "available_layers": [
        "community",
        "market",
        "official",
        "operational"
      ],
      "missing_layers": [],
      "layer_counts": {
        "community": 8,
        "market": 70,
        "official": 5,
        "operational": 9
      },
      "next_step": "GitHub releaseВ·star, package registry download, мұ„мҡ© кіөкі лҘј м¶”к°Җн•ҙ мұ„нғқ кі„мёөмқ„ ліҙк°•н•ңлӢӨ.",
      "quality_score": 95,
      "taxonomy_priority_score": 0,
      "article_count": 1155,
      "matched_count": 1150,
      "match_rate": 99.6,
      "source_count": 60,
      "dashboard_status": "active",
      "last_updated": "2026-04-25",
      "warnings": [],
      "warning_count": 0,
      "quality_origin": "BlogRadar/reports/techblog_20260428_quality.json",
      "data_origin": "BlogRadar/reports/techblog_20260425_summary.json",
      "tracked_coverage_pct": 0.0,
      "freshness_coverage_pct": null,
      "disabled_source_classification": {
        "awaiting_url_replacement": 0,
        "awaiting_secret": 0,
        "awaiting_smoke_test": 0,
        "upstream_section_missing": 0,
        "awaiting_partnership_review": 0,
        "accepted_backlog": 0
      },
      "disabled_source_classification_total": 0,
      "collection_errors": 0,
      "freshness_gap": 0,
      "stale_sources": 0,
      "missing_sources": 0,
      "unknown_event_date_sources": 0,
      "disabled_sources": 0,
      "total_sources": 78,
      "enabled_sources": 78,
      "tracked_sources": 0,
      "fresh_sources": 0,
      "not_tracked_sources": 78,
      "operational_priority": "P3",
      "taxonomy_priority": "T3",
      "risk_score": 12,
      "focus_area": "tracked_source_coverage"
    },
    {
      "repo": "MovieRadar",
      "display_name": "Movie",
      "category": "movie",
      "repo_class": "standard-radar",
      "domain_family": "media-entertainment",
      "primary_motion": "intelligence",
      "governance_profile": "low",
      "evidence_strategy": "official-operational",
      "readiness_status": "ready",
      "source_status": "к°•н•Ё",
      "available_layers": [
        "market",
        "official",
        "operational"
      ],
      "missing_layers": [],
      "layer_counts": {
        "market": 10,
        "official": 3,
        "operational": 5
      },
      "next_step": "көӯлӮҙ мҳҲл§Ө мҲңмң„, OTT Top 10, release calendar, audience ratingмқ„ лҚ”н•ңлӢӨ.",
      "quality_score": 95,
      "taxonomy_priority_score": 0,
      "article_count": 76,
      "matched_count": 76,
      "match_rate": 100.0,
      "source_count": 10,
      "dashboard_status": "active",
      "last_updated": "2026-04-25",
      "warnings": [
        "quality freshness gaps: stale=2, missing=0, unknown_event_date=0"
      ],
      "warning_count": 1,
      "quality_origin": "MovieRadar/reports/movie_20260428_quality.json",
      "data_origin": "MovieRadar/reports/movie_20260425_summary.json",
      "tracked_coverage_pct": 25.0,
      "freshness_coverage_pct": 33.3,
      "disabled_source_classification": {
        "awaiting_url_replacement": 0,
        "awaiting_secret": 0,
        "awaiting_smoke_test": 0,
        "upstream_section_missing": 0,
        "awaiting_partnership_review": 0,
        "accepted_backlog": 0
      },
      "disabled_source_classification_total": 0,
      "collection_errors": 0,
      "freshness_gap": 2,
      "stale_sources": 2,
      "missing_sources": 0,
      "unknown_event_date_sources": 0,
      "disabled_sources": 0,
      "total_sources": 12,
      "enabled_sources": 12,
      "tracked_sources": 3,
      "fresh_sources": 1,
      "not_tracked_sources": 9,
      "operational_priority": "P2",
      "taxonomy_priority": "T3",
      "risk_score": 8,
      "focus_area": "tracked_source_coverage"
    },
    {
      "repo": "PriceRadar",
      "display_name": "Price",
      "category": "price",
      "repo_class": "advanced-radar",
      "domain_family": "commerce-pricing",
      "primary_motion": "conversion",
      "governance_profile": "medium",
      "evidence_strategy": "market-led",
      "readiness_status": "ready",
      "source_status": "к°•н•Ё",
      "available_layers": [
        "community",
        "market",
        "operational"
      ],
      "missing_layers": [],
      "layer_counts": {
        "community": 6,
        "market": 26,
        "operational": 9
      },
      "next_step": "SKU к°ҖкІ© мқҙл Ҙ, мһ¬кі В·н’Ҳм Ҳ, м№ҙл“ңнҳңнғқВ·мҝ нҸ°к№Ңм§Җ м—°кІ°н•ҙ кө¬л§ӨмқҳмӮ¬кІ°м • м •нҷ•лҸ„лҘј лҚ” лҶ’мқёлӢӨ.",
      "quality_score": 95,
      "taxonomy_priority_score": 8,
      "article_count": 100,
      "matched_count": 100,
      "match_rate": 100.0,
      "source_count": 4,
      "dashboard_status": "active",
      "last_updated": "2026-04-24",
      "warnings": [],
      "warning_count": 0,
      "quality_origin": "PriceRadar/reports/price_20260408_quality.json",
      "data_origin": "PriceRadar/reports/price_20260424_summary.json",
      "tracked_coverage_pct": null,
      "freshness_coverage_pct": null,
      "disabled_source_classification": {
        "awaiting_url_replacement": 0,
        "awaiting_secret": 0,
        "awaiting_smoke_test": 0,
        "upstream_section_missing": 0,
        "awaiting_partnership_review": 0,
        "accepted_backlog": 1
      },
      "disabled_source_classification_total": 1,
      "collection_errors": 0,
      "freshness_gap": 0,
      "stale_sources": 0,
      "missing_sources": 0,
      "unknown_event_date_sources": 0,
      "disabled_sources": 0,
      "total_sources": 0,
      "enabled_sources": 0,
      "tracked_sources": 0,
      "fresh_sources": 0,
      "not_tracked_sources": 0,
      "operational_priority": "P3",
      "taxonomy_priority": "T3",
      "risk_score": 0,
      "focus_area": "stable"
    },
    {
      "repo": "TrendRadar",
      "display_name": "Trend",
      "category": "trend",
      "repo_class": "advanced-radar",
      "domain_family": "trend-discovery",
      "primary_motion": "attention",
      "governance_profile": "low",
      "evidence_strategy": "attention-led",
      "readiness_status": "ready",
      "source_status": "к°•н•Ё",
      "available_layers": [
        "attention",
        "community",
        "market",
        "official",
        "operational"
      ],
      "missing_layers": [],
      "layer_counts": {
        "attention": 11,
        "community": 5,
        "market": 5,
        "official": 6,
        "operational": 6
      },
      "next_step": "shoppingВ·conversion м§Җн‘ңлҘј лҚ” л„“нһҲкі  vertical keyword packмқ„ н‘ңмӨҖнҷ”н•ңлӢӨ.",
      "quality_score": 95,
      "taxonomy_priority_score": 4,
      "article_count": 200,
      "matched_count": 200,
      "match_rate": 100.0,
      "source_count": 1,
      "dashboard_status": "active",
      "last_updated": "2026-04-24",
      "warnings": [],
      "warning_count": 0,
      "quality_origin": "TrendRadar/reports/trend_quality.json",
      "data_origin": "TrendRadar/reports/trend_20260424_summary.json",
      "tracked_coverage_pct": null,
      "freshness_coverage_pct": null,
      "disabled_source_classification": {
        "awaiting_url_replacement": 0,
        "awaiting_secret": 0,
        "awaiting_smoke_test": 0,
        "upstream_section_missing": 0,
        "awaiting_partnership_review": 0,
        "accepted_backlog": 0
      },
      "disabled_source_classification_total": 0,
      "collection_errors": 0,
      "freshness_gap": 0,
      "stale_sources": 0,
      "missing_sources": 0,
      "unknown_event_date_sources": 0,
      "disabled_sources": 0,
      "total_sources": 0,
      "enabled_sources": 0,
      "tracked_sources": 0,
      "fresh_sources": 0,
      "not_tracked_sources": 0,
      "operational_priority": "P3",
      "taxonomy_priority": "T3",
      "risk_score": 0,
      "focus_area": "stable"
    }
  ]
}
